jipamlib_influx/__init__.py
jipamlib_influx/v1.py
jipamlib_influx-0.0.2.dist-info/METADATA
jipamlib_influx-0.0.2.dist-info/WHEEL
jipamlib_influx-0.0.2.dist-info/licenses/LICENSE
jipamlib_influx-0.0.2.dist-info/RECORD
