Metadata-Version: 2.1
Name: jipamlib_influx
Version: 0.0.2
Summary: jipam libs para conectar a influxdb
Project-URL: Homepage, https://github.com/jgajardog/jipamlib_influx
Author-email: jgajardo <jgajardo@gmail.com>
License-File: LICENSE
Classifier: License :: OSI Approved :: MIT License
Classifier: Operating System :: OS Independent
Classifier: Programming Language :: Python :: 3
Requires-Python: >=3.0
